{
  "message": "PREDICTIVE CHALLENGE",
  "challenges": [
    {
      "id": 1,
      "title": "BEAT THE GAME 1 HIGH SCORE!",
      "buckets": [
        {
          "description": "Predict any player to beat the Game 1 points benchmark by scoring 39 or more in any Game 2 matchup and you’ll win a pack! \uD83E\uDD73",
          "is_wildcard": false,
          "type": "LB",
          "count": 1,
          "is_team": false,
          "tier_breakers": [
            {
              "stats": "PTS",
              "order": "DESC"
            }
          ],
          "dates": [
            "04/17/2023"
          ]
        }
      ]
    }
  ]
}

